Niuniu/__init__.py
Niuniu/app.py
Niuniu/resource.py
Niuniu/server.py
Niuniu-0.0.6.dist-info/DESCRIPTION.rst
Niuniu-0.0.6.dist-info/METADATA
Niuniu-0.0.6.dist-info/RECORD
Niuniu-0.0.6.dist-info/WHEEL
Niuniu-0.0.6.dist-info/metadata.json
Niuniu-0.0.6.dist-info/top_level.txt
