Metadata-Version: 2.0
Name: Niuniu
Version: 0.0.6
Summary: A web RESTFul framework simple as 1+1
Home-page: https://github.com/bluicezhen/Niuniu
Author: Bluice Zhen
Author-email: bluice.zhen@gmail.com
License: GPL
Keywords: web framework werkzeug
Platform: UNKNOWN
Classifier: Development Status :: 5 - Production/Stable
Classifier: Intended Audience :: Developers
Classifier: License :: OSI Approved :: GNU General Public License v3 (GPLv3)
Classifier: Natural Language :: English
Classifier: Programming Language :: Python :: 3.6
Classifier: Programming Language :: Python :: 3 :: Only
Classifier: Programming Language :: Python :: Implementation :: CPython
Requires-Python: >=3.6, <4
Requires-Dist: Werkzeug
